epyseg/__init__.py
epyseg/__main__.py
epyseg/epygui.py
epyseg/img.py
epyseg/version.py
epyseg/IJ_ROIs/__init__.py
epyseg/IJ_ROIs/tools.py
epyseg/PATH/__init__.py
epyseg/PATH/tools.py
epyseg/SQLite_tools/__init__.py
epyseg/SQLite_tools/tools.py
epyseg/binary/__init__.py
epyseg/binary/tools.py
epyseg/binarytools/__init__.py
epyseg/binarytools/cell_center_detector.py
epyseg/clipboard_tools/__init__.py
epyseg/clipboard_tools/tools.py
epyseg/colors/__init__.py
epyseg/colors/tools.py
epyseg/command_line/__init__.py
epyseg/command_line/tools.py
epyseg/deeplearning/__init__.py
epyseg/deeplearning/deepl.py
epyseg/deeplearning/augmentation/__init__.py
epyseg/deeplearning/augmentation/meta.py
epyseg/deeplearning/augmentation/generators/__init__.py
epyseg/deeplearning/augmentation/generators/data.py
epyseg/deeplearning/augmentation/generators/data_augmentation_2.py
epyseg/deeplearning/augmentation/generators/meta.py
epyseg/deeplearning/callbacks/__init__.py
epyseg/deeplearning/callbacks/saver.py
epyseg/deeplearning/callbacks/stop.py
epyseg/deeplearning/docs/HQ_preds.md
epyseg/deeplearning/docs/__init__.py
epyseg/deeplearning/docs/channel_number_adjustement.md
epyseg/deeplearning/docs/data_augmentation.md
epyseg/deeplearning/docs/doc2html.py
epyseg/deeplearning/docs/getting_started.md
epyseg/deeplearning/docs/getting_started2.md
epyseg/deeplearning/docs/getting_started3.md
epyseg/deeplearning/docs/input_data.md
epyseg/deeplearning/docs/invert.md
epyseg/deeplearning/docs/load_model.md
epyseg/deeplearning/docs/model.md
epyseg/deeplearning/docs/model_parameters.md
epyseg/deeplearning/docs/model_selection.md
epyseg/deeplearning/docs/model_training_parameters.md
epyseg/deeplearning/docs/model_weights.md
epyseg/deeplearning/docs/output_data.md
epyseg/deeplearning/docs/output_preds.md
epyseg/deeplearning/docs/predict.md
epyseg/deeplearning/docs/preprocessing.md
epyseg/deeplearning/docs/preprocessing_output.md
epyseg/deeplearning/docs/pretrained_model.md
epyseg-0.1.52.dist-info/LICENSE
epyseg-0.1.52.dist-info/METADATA
epyseg-0.1.52.dist-info/WHEEL
epyseg-0.1.52.dist-info/top_level.txt
epyseg-0.1.52.dist-info/RECORD
