Metadata-Version: 2.1
Name: epyseg
Version: 0.1.52
Summary: A deep learning based tool to segment epithelial tissues. The epyseg GUI can be uesd to build, train or run custom networks
Home-page: https://github.com/baigouy/EPySeg
Author: Benoit Aigouy
Author-email: benoit.aigouy@gmail.com
License: BSD
Classifier: Programming Language :: Python :: 3
Classifier: License :: OSI Approved :: BSD License
Classifier: Operating System :: OS Independent
Requires-Python: >=3.6, <3.11
License-File: LICENSE
Requires-Dist: tensorflow <2.16.0
Requires-Dist: segmentation-models ==1.0.1
Requires-Dist: czifile
Requires-Dist: Markdown
Requires-Dist: matplotlib >=3.5.2
Requires-Dist: numpy
Requires-Dist: Pillow >=8.1.2
Requires-Dist: PyQt6
Requires-Dist: read-lif
Requires-Dist: scikit-image >=0.19.3
Requires-Dist: scipy >=1.7.3
Requires-Dist: scikit-learn >=1.0.2
Requires-Dist: tifffile >=2021.11.2
Requires-Dist: tqdm
Requires-Dist: natsort
Requires-Dist: numexpr
Requires-Dist: urllib3
Requires-Dist: qtawesome
Requires-Dist: pandas
Requires-Dist: numba
Requires-Dist: elasticdeform
Requires-Dist: roifile
Requires-Dist: prettytable
Requires-Dist: pyperclip
Requires-Dist: QtPy >=2.1.0
Requires-Dist: deprecated
